README.md
mathactive_site/__init__.py
mathactive_site/asgi.py
mathactive_site/settings.py
mathactive_site/urls.py
mathactive_site/wsgi.py
mathactive_web/__init__.py
mathactive_web/admin.py
mathactive_web/apps.py
mathactive_web/migrations/__init__.py
mathactive_web/models.py
mathactive_web/static/style.css
mathactive_web/templates/index.html
mathactive_web/tests.py
mathactive_web/views.py
mathactive_django-0.0.1.dist-info/WHEEL
mathactive_django-0.0.1.dist-info/METADATA
mathactive_django-0.0.1.dist-info/RECORD
